{
    "$schema": "https://app.blockstudio.dev/schema",
    "name": "wp2s/visual-studio-code-platform",
    "title": "Visual Studio Code",
    "category": "dev",
    "icon": "editor-code",
    "description": "",
    "supports": {
        "className": false,
        "customClassName": true,
        "align": [
            "full",
            "wide"
        ],
        "renaming": true,
        "color": {
            "background": true,
            "text": true
        }
    },
    "blockstudio": true
}